srwpy/SRWLIB_ExampleViewDataFile.py
srwpy/__init__.py
srwpy/srwl_bl.py
srwpy/srwl_uti_brightness.py
srwpy/srwl_uti_cryst.py
srwpy/srwl_uti_mag.py
srwpy/srwl_uti_opt.py
srwpy/srwl_uti_smp.py
srwpy/srwl_uti_smp_rnd_obj2d.py
srwpy/srwl_uti_smp_rnd_obj3d.py
srwpy/srwl_uti_src.py
srwpy/srwl_uti_und.py
srwpy/srwlib.py
srwpy/srwlpy.so
srwpy/uti_cp_prj.py
srwpy/uti_io.py
srwpy/uti_io_genesis.py
srwpy/uti_mag.py
srwpy/uti_math.py
srwpy/uti_math_eigen.py
srwpy/uti_parse.py
srwpy/uti_plot.py
srwpy/uti_plot_com.py
srwpy/uti_plot_matplotlib.py
srwpy/examples/SRWLIB_Example01.py
srwpy/examples/SRWLIB_Example01_kick_matr.py
srwpy/examples/SRWLIB_Example02.py
srwpy/examples/SRWLIB_Example03.py
srwpy/examples/SRWLIB_Example04.py
srwpy/examples/SRWLIB_Example05.py
srwpy/examples/SRWLIB_Example06.py
srwpy/examples/SRWLIB_Example06_PETRA.py
srwpy/examples/SRWLIB_Example07.py
srwpy/examples/SRWLIB_Example08.py
srwpy/examples/SRWLIB_Example09.py
srwpy/examples/SRWLIB_Example10.py
srwpy/examples/SRWLIB_Example11.py
srwpy/examples/SRWLIB_Example12.py
srwpy/examples/SRWLIB_Example13.py
srwpy/examples/SRWLIB_Example14.py
srwpy/examples/SRWLIB_Example15.py
srwpy/examples/SRWLIB_Example16.py
srwpy/examples/SRWLIB_Example17.py
srwpy/examples/SRWLIB_Example18.py
srwpy/examples/SRWLIB_Example19.py
srwpy/examples/SRWLIB_Example20.py
srwpy/examples/SRWLIB_Example21.py
srwpy/examples/SRWLIB_ExamplesRunAll.py
srwpy/examples/__init__.py
srwpy/examples/data_example_01/epu49HEtot.dat
srwpy/examples/data_example_01/epu49LVtot.dat
srwpy/examples/data_example_01/epu49cen.dat
srwpy/examples/data_example_01/epu49he_kick_m.dat
srwpy/examples/data_example_01/epu49term1.dat
srwpy/examples/data_example_01/epu49term2.dat
srwpy/examples/data_example_02/dummy.txt
srwpy/examples/data_example_03/dummy.txt
srwpy/examples/data_example_04/dummy.txt
srwpy/examples/data_example_05/segmented.dat
srwpy/examples/data_example_06/dummy.txt
srwpy-4.1.1.dist-info/METADATA
srwpy-4.1.1.dist-info/WHEEL
srwpy-4.1.1.dist-info/entry_points.txt
srwpy-4.1.1.dist-info/top_level.txt
srwpy-4.1.1.dist-info/RECORD
