Metadata-Version: 2.4
Name: srwpy
Version: 4.1.1
Summary: This is SRW for Python
Home-page: http://github.com/ochubar/SRW
Author: O. Chubar et al.
Author-email: chubar@bnl.gov
Requires-Dist: h5py
Requires-Dist: matplotlib
Requires-Dist: numpy
Requires-Dist: pillow
Requires-Dist: scikit-learn
Requires-Dist: scipy
Dynamic: author
Dynamic: author-email
Dynamic: description
Dynamic: description-content-type
Dynamic: home-page
Dynamic: requires-dist
Dynamic: summary
